fylearn/__init__.py
fylearn/_version.py
fylearn/fpcga.py
fylearn/fpt.py
fylearn/frr.py
fylearn/fuzzylogic.py
fylearn/ga.py
fylearn/garules.py
fylearn/jaya.py
fylearn/local_search.py
fylearn/nfpc.py
fylearn/nonstationary.py
fylearn/rafpc.py
fylearn/tlbo.py
fylearn-0.2.1.dist-info/LICENSE
fylearn-0.2.1.dist-info/WHEEL
fylearn-0.2.1.dist-info/METADATA
fylearn-0.2.1.dist-info/RECORD
