Metadata-Version: 2.1
Name: fylearn
Version: 0.2.1
Summary: Fuzzy Machine Learning Algorithms
Keywords: machine learning,fuzzy logic,scikit-learn,fuzzy systems
Maintainer-email: Søren Atmakuri Davidsen <soren@atmakuridavidsen.com>
Classifier: Operating System :: OS Independent
Classifier: License :: OSI Approved :: MIT License
Classifier: Programming Language :: Python :: 3.12
Classifier: Topic :: Scientific/Engineering :: Artificial Intelligence
Classifier: Topic :: Scientific/Engineering :: Information Analysis
Classifier: Intended Audience :: Science/Research
Classifier: Intended Audience :: Education
Classifier: Intended Audience :: Developers
Requires-Dist: numpy>=1.17
Requires-Dist: scipy>=1.3
Requires-Dist: scikit-learn>=0.22
Requires-Dist: tox ; extra == "dev"
Requires-Dist: tox-gh-actions ; extra == "dev"
Project-URL: Issues, https://github.com/sorend/fylearn/issues
Project-URL: Repository, https://github.com/sorend/fylearn.git
Provides-Extra: dev
